everart/__init__.py
everart/client.py
everart/client_interface.py
everart/generations.py
everart/images.py
everart/models.py
everart/util.py
everart-1.1.0.dist-info/LICENSE
everart-1.1.0.dist-info/METADATA
everart-1.1.0.dist-info/WHEEL
everart-1.1.0.dist-info/top_level.txt
everart-1.1.0.dist-info/RECORD
