Metadata-Version: 2.1
Name: everart
Version: 1.1.0
Summary: Python client for EverArt REST API
Author: NewCompute, Inc.
License: 
Project-URL: homepage, https://everart.ai
Project-URL: repository, https://github.com/newcompute-ai/everart-python
Requires-Python: >=3.8
License-File: LICENSE
Requires-Dist: python-dotenv~=1.0
Requires-Dist: requests~=2.32
Provides-Extra: dev
Requires-Dist: pytest; extra == "dev"
